pdx/CodeBlock.py
pdx/Config.py
pdx/Console.py
pdx/Encryptor.py
pdx/Executor.py
pdx/Log.py
pdx/Session.py
pdx/__init__.py
pdx/date_service.py
pdx/file_service.py
pdx/utility_service.py
pdx/db/ConnectionHolder.py
pdx/db/OracleConnection.py
pdx/db/Query.py
pdx/db/__init__.py
pdx/db/banner_service.py
pdx/git/BitBucket.py
pdx/git/GitWrapper.py
pdx/git/__init__.py
pdx/git/actions.py
pdx/git/remote.py
pdx/git/repo.py
pdx/git/utility.py
pdx/web/__init__.py
pdx/web/jwt.py
tests/__init__.py
tests/test_basics.py
tests/test_code_block.py
tests/test_dates.py
tests/test_executor.py
tests/test_git.py
tests/test_oracle.py
tests/test_utilities.py
pdx_lib-0.0.3.dist-info/METADATA
pdx_lib-0.0.3.dist-info/WHEEL
pdx_lib-0.0.3.dist-info/top_level.txt
pdx_lib-0.0.3.dist-info/RECORD
