Metadata-Version: 2.1
Name: pdx-lib
Version: 0.0.3
Summary: Library to speed up common scripting tasks at PSU
Home-page: https://github.com/mikegostomski/pdx
Author: Mike Gostomski
Author-email: mjg@pdx.edu
License: MIT License
Platform: UNKNOWN
Classifier: License :: OSI Approved :: MIT License
Classifier: Operating System :: OS Independent
Classifier: Programming Language :: Python :: 3.6
Requires-Dist: pycryptodome
Requires-Dist: requests
Requires-Dist: pyyaml
Requires-Dist: cx-Oracle
Requires-Dist: gitpython
